Workbook

Sheet top 4000
A1: RANK NEW | B1: WORD | C1: IPA | D1: ENGLISH | E1: FREQUENCY | F1: DP RANK | G1: EXAMPLE SENTENCE | Q1: RANK NEW
A2: 1 | B2: ที่ | C2: tʰîː | D2: at | E2: 773568 | F2: 94.347748 | G2: เขาได้รับรางวัลที่ 1 ในการประกวดวาดภาพ | Q2: 1
A3: 2 | B3: ได้ | C3: dâj | D3: can | E3: 378303 | F3: 97.140413 | G3: นักท่องเที่ยวได้ข้อมูลนี้จากหนังสือนำเที่ยว | Q3: 2
A4: 3 | B4: จะ | C4: tɕàʔ | D4: will | E4: 481733 | F4: 96.333916 | G4: การอนุรักษ์สิ่งแวดล้อมจะสัมฤทธิ์ผลได้ถ้าทุกคนร่วมมือกัน | Q4: 3
A5: 4 | B5: นี้ | C5: níː | D5: this | E5: 165729 | F5: 97.741623 | G5: ศาลมีคำพิพากษาถึงที่สุดว่าการสมรสของบุคคลคู่นี้ เป็นโมฆะแล้ว | Q5: 4
A6: 5 | B6: ว่า | C6: wâː | D6: that; think | E6: 344636 | F6: 95.191006 | G6: ”ภาษา” เป็นคำที่มาจากรากศัพท์ “ภาษ” แปลว่าพูด | Q6: 5
A7: 6 | B7: เป็น | C7: pen | D7: is; be able | E7: 515715 | F7: 91.512864 | G7: แมวที่อาจารย์เลี้ยงไว้มีอยู่หลายตัวเป็นแมวจรจัด | Q7: 6
A8: 7 | B8: มี | C8: miː | D8: have; there is | E8: 480238 | F8: 91.973274 | G8: อาหารหลักที่สำคัญต่อชีวิตเรามี 5 หมู่ | Q8: 7
A9: 8 | B9: ให้ | C9: hâj | D9: for | E9: 345123 | F9: 93.702706 | G9: ยานอนหลับและยากล่อมประสาทห้ามซื้อกินเอง ถ้าจะกินต้องให้หมอสั่งยา | Q9: 8
A10: 9 | B10: ต้อง | C10: tɔ̂ŋ | D10: must | E10: 146008 | F10: 97.233763 | G10: มนุษย์เราจำเป็นต้องใช้ชีวิตร่วมกับผู้อื่น | Q10: 9
A11: 10 | B11: ของ | C11: kʰɔ̌ːŋ | D11: of | E11: 480700 | F11: 89.492973 | G11: ชมรมค่ายอาสาพัฒนาขอบริจาคของที่เหลือใช้จากประชาชนทั่วไป | Q11: 10
A12: 11 | B12: กับ | C12: kàp | D12: with | E12: 188374 | F12: 95.270585 | G12: เขาวางเหยื่อล่อเพื่อให้หนูมาติดกับ | Q12: 11
A13: 12 | B13: ไม่ | C13: mâj | D13: not | E13: 435872 | F13: 88.183208 | G13: นมข้นหวานก็เป็นนมที่มีความหวานมากเกินไปไม่เหมาะสำหรับเด็ก | Q13: 12
... A140: 139 | B140: เดิม | C140: dɤːm | D140: original; before | E140: 13893 | F140: 93.244378 | G140: แต่เดิมเราผลิตสินค้าได้น้อยมาก เพราะยังไม่มีเทคโนโลยีรองรับเพียงพอ | Q140: 139
A141: 140 | B141: ได้รับ | C141: dâj ráp | D141: receive | E141: 39689 | F141: 80.688554 | G141: เขาได้รับเงินรางวัลจำนวนมากมาย | M141: repeat | Q141: 140
A142: 141 | B142: น้ำ | C142: náːm | D142: water | E142: 32937 | F142: 83.936453 | G142: พวกเราก่อกองไฟอยู่ตรงริมน้ำ แล้วกางเต็นท์ห่างออกไปประมาณ 2 เมตร | Q142: 141
A143: 142 | B143: อย่างไร | C143: jàːŋ raj | D143: how | E143: 16555 | F143: 91.813836 | G143: ความงามความดีมนุษย์ สร้างขึ้นมาได้อย่างไร | Q143: 142
A144: 143 | B144: ยิ่ง | C144: jîŋ | D144: more | E144: 20860 | F144: 89.624446 | G144: การถ่ายทอดอารมณ์ให้กับภาพนั้นเป็นสิ่งสำคัญยิ่ง | Q144: 143
A145: 144 | B145: ฝ่าย | C145: fàːj | D145: party; side | E145: 23633 | F145: 88.127682 | G145: การทำให้เครื่องใหม่ครอบคลุมรุ่นเก่านั้น มีประโยชน์ด้วยกันทุกฝ่าย | Q145: 144
A146: 145 | B146: บ้าน | C146: bâːn | D146: home | E146: 36957 | F146: 81.39837 | G146: ประชากรไทยที่มีคอมพิวเตอร์ใช้ในบ้านเพิ่มจำนวนมากขึ้นทุกๆ วัน | Q146: 145
A147: 146 | B147: คำ | C147: kʰam | D147: word | E147: 33546 | F147: 83.039721 | G147: เสียงของแต่ละคนนั้นพูดแต่ละครั้งจะไม่เหมือนกัน แม้จะพูดคำเดียวกันหรือประโยคเดียวกันก็ตาม | Q147: 146
A148: 147 | B148: พบ | C148: pʰóp | D148: meet; find | E148: 28641 | F148: 85.428465 | G148: นักเรียนใหม่พบอาจารย์ที่ปรึกษาในวันเปิดภาคเรียน | Q148: 147
A149: 148 | B149: เข้าใจ | C149: kʰâw tɕaj | D149: understand | E149: 20416 | F149: 89.583601 | G149: ถ้าเธอเข้าใจเธอก็สามารถทำข้อสอบได้ ไม่ว่าจะออกมาในรูปแบบไหน | Q149: 148
A150: 149 | B150: อัน | C150: ʔan | D150: piece (classifier) | E150: 29808 | F150: 84.489317 | G150: ปัญหานี้เป็นปัญหาที่สำคัญที่สุดอันหนึ่งในการออกแบบโปรแกรม | Q150: 149
A151: 150 | B151: ส่ง | C151: sòŋ | D151: send | E151: 24610 | F151: 87.07559 | G151: สถาปนิกกลุ่มนี้ส่งแบบแปลนถึงกันและกันผ่านทางสายโทรศัพท์ | Q151: 150
A152: 151 | B152: ที่อยู่ | C152: tʰîː jùː | D152: address | E152: 11742 | F152: 93.828172 | G152: ผู้ที่จะรับ-ส่งจดหมายอิเล็กทรอนิกส์ได้จะต้องมีที่อยู่หรือที่เรียกว่า e-mail address เสียก่อน | Q152: 151
A153: 152 | B153: มัน | C153: man | D153: it | E153: 64569 | F153: 66.037972 | G153: บ้านฉันที่อิสานปลูกมันไว้เป็นแถวๆ เอาหัวมันมาปรุงอาหารได้ | Q153: 152
... A331: 330 | B331: ชนิด | C331: tɕʰá nít | D331: class; sort; type | E331: 13419 | F331: 80.621122 | G331: สินค้าราคาจะแพงหรือไม่แพงขึ้นอยู่กับชนิดของวัตถุดิบที่ใช้ | Q331: 330
A332: 331 | B332: ประชาชน | C332: pràʔ tɕʰaː tɕʰon | D332: citizents | E332: 17178 | F332: 74.894342 | G332: วิถีการดำเนินชีวิตความรู้สึกนึกคิดของประชาชนเปลี่ยนแปลงไป | M332: vs ประชากร | Q332: 331
A333: 332 | B333: กรณี | C333: kà rá niː | D333: case | E333: 23948 | F333: 64.745365 | G333: คณะกรรมการมีความเห็นเป็น 3 กรณี แต่จะมีการประชุมเพื่อหาข้อยุติ | Q333: 332
A334: 333 | B334: ตา | C334: taː | D334: eye | E334: 22204 | F334: 67.265212 | G334: ตาข่ายดักปลาจะมีตาถี่ห่างหลายขนาด | Q334: 333
A335: 334 | B335: ปัจจุบัน | C335: pàt tɕùʔ ban | D335: present | E335: 14270 | F335: 78.871373 | G335: ปัจจุบัน คอมพิวเตอร์ถือได้ว่ามีความสำคัญอย่างยิ่งสำหรับธุรกิจ | Q335: 334
A336: 335 | B336: ใส่ | C336: sàj | D336: put | E336: 15767 | F336: 76.559818 | G336: หากเปิดเครื่องคอมพิวเตอร์แล้วพบคำสั่งล็อกออน ผู้ใช้ต้องใส่รหัสผ่าน เพื่อที่จะเข้าไปใช้เครื่องได้ | Q336: 335
A337: 336 | B337: รถ | C337: rót | D337: car | E337: 18443 | F337: 72.272553 | G337: ถนนสุขุมวิทในช่วงเลิกงานมีปริมาณรถมากที่สุดกว่าถนนสายอื่นๆ | Q337: 336
A338: 337 | B338: ขาด | C338: kʰàːt | D338: lack; incomplete | E338: 9578 | F338: 85.570352 | G338: เสื้อเขาขาดเป็นริ้วๆ เพราะโดนคนร้ายเอามีดฟัน | Q338: 337
A339: 338 | B339: ข้อ | C339: kʰɔ̂ː | D339: article; joint | E339: 22564 | F339: 65.937838 | G339: พระผูกสายสิญจน์ที่ข้อมือให้ผู้สืบชะตาทุกคน | Q339: 338
A340: 339 | B340: รัฐ | C340: rát | D340: state | E340: 18929 | F340: 71.397223 | G340: รัฐควรจัดหาทุนรอนมาส่งเสริมงานวิจัยทางด้านนี้มากๆ | Q340: 339
A341: 340 | B341: หลัก | C341: làk | D341: main; principle | E341: 17609 | F341: 73.337677 | G341: จิตวิเคราะห์หมายถึง วิธีการรักษาที่เน้นวิธีหลักคือการปล่อยให้คนไข้ได้พูดอย่างอิสระ | Q341: 340
A342: 341 | B342: สามี | C342: sǎː miː | D342: husband | E342: 5503 | F342: 91.65766 | G342: สามีต้องขยันทำงานตัวเป็นเกลียว เพื่อหาเงินมาผ่อนบ้านในแต่ละเดือน | Q342: 341
A343: 342 | B343: เหนือ | C343: nɯ̌ːa | D343: above; North | E343: 8374 | F343: 87.250694 | G343: ในสมัยโบราณผู้เป็นนายมีอำนาจเหนือทาสตามกฎหมายโดยมีสิทธิใช้ให้ทำงานได้ทุกอย่าง | Q343: 342
A344: 343 | B344: พี่ | C344: pʰîː | D344: older sibling | E344: 28648 | F344: 56.243843 | G344: พี่ของเขาเลี้ยงดูเขาตั้งแต่ยังเด็ก พอโตขึ้นก็ยังต้องเลี้ยงเขาเหมือนเดิม | Q344: 343
... A533: 532 | B533: พ่อแม่ | C533: pʰɔ̂ː mɛ̂ː | D533: parents | E533: 5713 | F533: 85.546018 | G533: พ่อแม่มีสิทธิ์ในการจัดการศึกษาของลูก | Q533: 532
A534: 533 | B534: เรียบร้อย | C534: rîːap rɔ́ːj | D534: be ready; be polite | E534: 5593 | F534: 85.817074 | G534: ลูกสาวคุณเรียบร้อย น่าชื่นชมจริงๆ | L534: tidy | Q534: 533
A535: 534 | B535: ตกลง | C535: tòk loŋ | D535: agree | E535: 6623 | F535: 83.160131 | G535: รัฐบาลยอมตกลงที่จะจ่ายเงินค่าเสียหายให้แก่ชาวบ้านที่มาร้องเรียน | Q535: 534
A536: 535 | B536: ไกล | C536: klaj | D536: far | E536: 6861 | F536: 82.485704 | G536: เจ้าเหมียววิ่งหนีเจ้าด่างไปไกล | Q536: 535
A537: 536 | B537: ทิ้ง | C537: tʰíŋ | D537: throw (away) | E537: 7596 | F537: 80.588357 | G537: เขาไม่มีความรับผิดชอบ ทิ้งลูกทิ้งเมีย | Q537: 536
A538: 537 | B538: เสร็จ | C538: sèt | D538: completed | E538: 7543 | F538: 80.695465 | G538: คราวนี้พวกเราต้องเสร็จมันแน่ๆ เพราะมันวางแผนมาดี | Q538: 537
A539: 538 | B539: ไหม | C539: mǎj | D539: question particle | E539: 12300 | F539: 68.388829 | G539: งานช่างที่ผู้หญิงทางภาคเหนือทำส่วนใหญ่เป็นงานทอผ้าและเลี้ยงไหม | Q539: 538
A540: 539 | B540: ข่าว | C540: kʰàːw | D540: news | E540: 9517 | F540: 75.461203 | G540: ปัจจุบันมีข่าวอาชาญากรรมตามหน้าหนังสือพิมพ์มากขึ้นทุกวัน | Q540: 539
A541: 540 | B541: ประกาศ | C541: pràʔ kàːt | D541: announce | E541: 11545 | F541: 70.225147 | G541: รัฐบาลปิดประกาศให้ประชาชนไปเสียภาษี | Q541: 540
A542: 541 | B542: มหา | C542: má hǎː | D542: great | E542: 5171 | F542: 86.644225 | G542: เจดีย์วัดพระประธมเป็นมหาเจดีย์ ใหญ่กว่าพระเจดีย์ในสยามประเทศทุกๆ แห่ง | Q542: 541
A543: 542 | B543: ดำ | C543: dam | D543: black | E543: 8480 | F543: 78.092088 | G543: กระเป๋าสตางค์สีดำที่วางอยู่บนโต๊ะหายไป | Q543: 542
A544: 543 | B544: วง | C544: woŋ | D544: circle | E544: 5559 | F544: 85.574072 | G544: อาจารย์ปรีชา อรัญจารีเป็นผู้ชักนำ “ฝน ธนสุนทร“ เข้าสู่วงการเพลงลูกทุ่งเป็นคนแรก | Q544: 543
A545: 544 | B545: พระเจ้า | C545: pʰráʔ tɕâw | D545: God | E545: 5137 | F545: 86.580964 | G545: ศาสนาบางศาสนาเชื่อว่าพระเจ้าคือผู้บันดาลทุกสิ่งทุกอย่างให้กับมนุษย์ | Q545: 544
A546: 545 | B546: ชี้ | C546: tɕʰíː | D546: point | E546: 5280 | F546: 86.104115 | G546: อาจารย์ใช้ไม้บรรทัดชี้ตัวอักษรบนกระดาษดำ | Q546: 545
A547: 546 | B547: ฉบับ | C547: tɕʰà bàp | D547: issue | E547: 9358 | F547: 75.325284 | G547: บ้านนี้รับหนังสือพิมพ์วันละ 2 ฉบับ | L547: fine)(*&^% | Q547: 546
A548: 547 | B548: เกือบ | C548: kɯ̀ːap | D548: almost; close to | E548: 7139 | F548: 81.128852 | G548: ขั้นตอนระหว่างกระบวนการแปลจะมีการแก้ไขแทรกอยู่ด้วยเกือบทุกขั้นตอน | Q548: 547
A549: 548 | B549: สุด | C549: sùt | D549: end | E549: 7858 | F549: 79.136357 | G549: เขาได้อยู่ลู่ในสุดเลยได้เปรียบผู้เข้าแข่งขันคนอื่น | Q549: 548
A550: 549 | B550: แดง | C550: dɛːŋ | D550: red | E550: 9379 | F550: 75.035301 | G550: ไม้ฝางเป็นไม้ที่ใช้สำหรับย้อมสีเสื้อผ้าให้เป็นสีแดง | Q550: 549
A551: 550 | B551: อาการ | C551: ʔaː kaːn | D551: symptom | E551: 12757 | F551: 66.008758 | G551: แพทย์ใช้ยาปฏิชีวนะบำบัดอาการอักเสบของแผล | Q551: 550
A552: 551 | B552: แหล่ง | C552: lɛ̀ŋ | D552: source; place, venue, spot | E552: 7125 | F552: 81.014081 | G552: ที่นี่เป็นแหล่งอารยธรรมแรกเริ่มของมนุษย์ และล่มสลายไปนานนมแล้ว | Q552: 551
A553: 552 | B553: สถานที่ | C553: sà tʰǎːn tʰîː | D553: location | E553: 6907 | F553: 81.533742 | G553: นักประท้วงถูกนำตัวไปยังสถานที่อีกแห่งหนึ่งอย่างรวดเร็ว | Q553: 552
A554: 553 | B554: ชุมชน | C554: tɕʰum tɕʰon | D554: community | E554: 9664 | F554: 74.124434 | G554: ชาวไร่สับปะรดได้รวมตัวเป็นชุมชนขึ้นมาเพื่อดูแลผลประโยชน์ซึ่งกันและกัน | Q554: 553
A555: 554 | B555: สิทธิ | C555: sìt tʰíʔ | D555: claim; right | E555: 15035 | F555: 59.615203 | G555: เยาวชนและบุคคลซึ่งพิการ หรือทุพพลภาพ มีสิทธิได้รับการศึกษาอบรมขั้นพื้นฐานจากรัฐ | Q555: 554
A556: 555 | B556: บท | C556: bòt | D556: chapter | E556: 9763 | F556: 73.700263 | G556: ส่วนของเธอรับผิดชอบอ่านไป 3 บท | Q556: 555
A557: 556 | B557: สนับสนุน | C557: sà nàp sà nǔn | D557: support | E557: 9351 | F557: 74.774899 | G557: ผู้นำควรสนับสนุนให้สมาชิกมีส่วนร่วมในการออกความคิดเห็นและตัดสินปัญหา | Q557: 556
A558: 557 | B558: ทำไม | C558: tʰam maj | D558: why | E558: 14964 | F558: 59.625169 | G558: เขาเริ่มสืบค้นว่าทำไมเขา และเพื่อนมนุษย์รอบๆ ตัวจึงปฏิบัติต่อกันและกันเยี่ยงนั้น | Q558: 557
A559: 558 | B559: ชม | C559: tɕʰom | D559: admire | E559: 5980 | F559: 83.829693 | G559: ประชาสัมพันธ์ของทางโรงแรมเชิญชวนผู้ที่สนใจไปชมนิทรรศการคอมพิวเตอร์ไทย | Q559: 558
... A894: 893 | B894: กรม | C894: krom | D894: department (government) | E894: 7614 | F894: 63.611411 | G894: จากผลสำรวจพบว่าเจ้าหน้าที่ของกรมการบินพลเรือนทหารบางนายไม่เห็นด้วยกับร่างกฎหมายการบินฉบับแก้ไขใหม่ | Q894: 893
A895: 894 | B895: กฎ | C895: kòt | D895: rule; regulation | E895: 3693 | F895: 82.320572 | G895: ตัวเลขที่ใช้มีเพียงศูนย์และหนึ่งเท่านั้น กฎการคำนวณจึงง่าย | L895: combine | Q895: 894
A896: 895 | B896: รอง | C896: rɔːŋ | D896: secondary, vice-; support from below | E896: 6678 | F896: 67.950134 | G896: ถ้าเป็นเรื่องอย่างนี้แล้ว เขาไม่รองใครแน่ | Q896: 895
A897: 896 | B897: ยังไง | C897: jaŋ ŋaj | D897: any way; whichever way | E897: 9819 | F897: 52.837071 | G897: คุณจะรู้ได้ยังไงว่าจะเกิดอะไรขึ้นในอนาคต | Q897: 896
A898: 897 | B898: ยื่น | C898: jɯ̂ːn | D898: reach; stick out | E898: 6746 | F898: 67.556108 | G898: ฝ่ายรัฐบาลได้ยื่นคำแถลงเป็นหนังสือต่อศาลรัฐธรรมนูญ | Q898: 897
A899: 898 | B899: ระบาย | C899: ráʔ baːj | D899: paint, release | E899: 2267 | F899: 89.089001 | G899: หากระบายสีเขียวเข้าไป ภาพนี้ก็คงจะเหมือนจริงขึ้นอีก | Q899: 898
A900: 899 | B900: ยาม | C900: jaːm | D900: guard; time | E900: 5412 | F900: 73.949066 | G900: การนวดถือว่าเป็นการบำบัดดูแลสุขภาพในยามเจ็บป่วยวิธีหนึ่ง | Q900: 899
A901: 900 | B901: พักผ่อน | C901: pʰák pʰɔ̀ːn | D901: rest | E901: 1888 | F901: 90.90066 | G901: เราควรออกกำลังกาย บริโภคอาหารให้ถูกสุขลักษณะ และพักผ่อนให้เพียงพอ | Q901: 900
A902: 901 | B902: รูปร่าง | C902: rûːp râːŋ | D902: shape | E902: 2564 | F902: 87.63364 | G902: ผู้หญิงพยายามเข้มงวดในการกินอาหารเพื่อไม่ให้รูปร่างอ้วนเผละ | Q902: 901
A903: 902 | B903: เอกชน | C903: ʔèːk kà tɕʰon | D903: private | E903: 5772 | F903: 72.135205 | G903: คดีแพ่งเป็นเรื่องระหว่างเอกชนต่อเอกชน | Q903: 902
A904: 903 | B904: พฤติกรรม | C904: pʰrɯ́ʔ tìʔ kam | D904: behavior | E904: 7695 | F904: 62.786949 | G904: คนใกล้ชิดของหมอเปรม 2 คน เป็นผู้ที่มีพฤติกรรมน่าสงสัย | Q904: 903
A905: 904 | B905: ภัย | C905: pʰaj | D905: disaster | E905: 4381 | F905: 78.807576 | G905: หากเราไม่ปฏิบัติตามคำสั่งอาจจะมีภัยมาถึงตัวเองอย่างแน่นอน | Q905: 904
A906: 905 | B906: สื่อ | C906: sɯ̀ː | D906: media | E906: 5925 | F906: 71.056539 | G906: เราเรียนภาษาเพื่อสื่อข่าวสารกันมากกว่าเพื่อจะได้สืบต่อและสร้างสรรค์วัฒนธรรมทางภาษา | Q906: 905
A907: 906 | B907: อุปกรณ์ | C907: ʔùʔ pà kɔːn | D907: equipment | E907: 3885 | F907: 81.015514 | G907: สถาบันราชภัฏยังขาดแคลนวัสดุอุปกรณ์ในการจัดการศึกษาและเทคโนโลยีช่วยสอนจำนวนมาก | Q907: 906
... A4001: 4000 | B4001: ชักจูง | C4001: tɕʰák tɕuːŋ | D4001: induce; persuade | E4001: 468 | F4001: 64.733017 | G4001: รัฐบาลจะชักจูงจีนและอินเดียให้สัตยาบันพิธีสารดังกล่าวในเรื่องปัญหาการค้าระหว่างประเทศ | Q4001: 4000

Sheet thai language top 1000
A1: McFarland's Top 1000 Thai Word List | C1: check 1 | D1: check 2 | E1: check 3 | F1: check 4
A2: word | B2: add<<
A3: ก็ | B3: also, likewise, as a result, subsequently | C3: =VLOOKUP(A3,[1]checker!$A:$C,1,FALSE) -> ก็ | D3: =VLOOKUP(A3,[1]checker!$A:$C,3,FALSE) -> then | E3: =VLOOKUP(A3,'top 4000'!$B:$Q,3,FALSE) -> then | F3: =VLOOKUP(A3,'top 4000'!$B:$Q,16,FALSE) -> 29
A4: กฎหมาย | B4: law, statute, enactment, rule | C4: =VLOOKUP(A4,[1]checker!$A:$C,1,FALSE) -> กฎหมาย | D4: =VLOOKUP(A4,[1]checker!$A:$C,3,FALSE) -> law | E4: =VLOOKUP(A4,'top 4000'!$B:$Q,3,FALSE) -> law | F4: =VLOOKUP(A4,'top 4000'!$B:$Q,16,FALSE) -> 389
A5: กร | B5: hand, arm | C5: =VLOOKUP(A5,[1]checker!$A:$C,1,FALSE) -> กร | D5: =VLOOKUP(A5,[1]checker!$A:$C,3,FALSE) -> worker; hand; sunlight | E5: =VLOOKUP(A5,'top 4000'!$B:$Q,3,FALSE) -> worker; hand; sunlight | F5: =VLOOKUP(A5,'top 4000'!$B:$Q,16,FALSE) -> 957
A6: กรกฎาคม | B6: July | C6: =VLOOKUP(A6,[1]checker!$A:$C,1,FALSE) -> #N/A | D6: =VLOOKUP(A6,[1]checker!$A:$C,3,FALSE) -> #N/A | E6: =VLOOKUP(A6,'top 4000'!$B:$Q,3,FALSE) -> july | F6: =VLOOKUP(A6,'top 4000'!$B:$Q,16,FALSE) -> 2215
A7: กรม | B7: department, bureau, regiment of soldier | C7: =VLOOKUP(A7,[1]checker!$A:$C,1,FALSE) -> กรม | D7: =VLOOKUP(A7,[1]checker!$A:$C,3,FALSE) -> department (government) | E7: =VLOOKUP(A7,'top 4000'!$B:$Q,3,FALSE) -> department (government) | F7: =VLOOKUP(A7,'top 4000'!$B:$Q,16,FALSE) -> 893
A8: กรรม | B8: deed, action, performance, doing, sin, wrong-doing, transgression | C8: =VLOOKUP(A8,[1]checker!$A:$C,1,FALSE) -> กรรม | D8: =VLOOKUP(A8,[1]checker!$A:$C,3,FALSE) -> deed; karma | E8: =VLOOKUP(A8,'top 4000'!$B:$Q,3,FALSE) -> deed; karma | F8: =VLOOKUP(A8,'top 4000'!$B:$Q,16,FALSE) -> 886
A9: กรรมการ | B9: committee, committee, member, commission, board, referee, judge, umpire | C9: =VLOOKUP(A9,[1]checker!$A:$C,1,FALSE) -> #N/A | D9: =VLOOKUP(A9,[1]checker!$A:$C,3,FALSE) -> #N/A | E9: =VLOOKUP(A9,'top 4000'!$B:$Q,3,FALSE) -> committee | F9: =VLOOKUP(A9,'top 4000'!$B:$Q,16,FALSE) -> 1088
A10: กระ | B10: freckle(s), spot(s), hawksbil turtle, hawk turtle, sea turtle, Eretmochelys, Imbricata | C10: =VLOOKUP(A10,[1]checker!$A:$C,1,FALSE) -> #N/A | D10: =VLOOKUP(A10,[1]checker!$A:$C,3,FALSE) -> #N/A | E10: =VLOOKUP(A10,'top 4000'!$B:$Q,3,FALSE) -> #N/A | F10: =VLOOKUP(A10,'top 4000'!$B:$Q,16,FALSE) -> #N/A
A11: กระจาย | B11: disperse, diffuse, dispel, scatter, dissipate, disseminate, disperse, scatter, spread, spread, expand, extend | C11: =VLOOKUP(A11,[1]checker!$A:$C,1,FALSE) -> กระจาย | D11: =VLOOKUP(A11,[1]checker!$A:$C,3,FALSE) -> spread | E11: =VLOOKUP(A11,'top 4000'!$B:$Q,3,FALSE) -> spread | F11: =VLOOKUP(A11,'top 4000'!$B:$Q,16,FALSE) -> 803
A12: กระด้าง | B12: be tough, be stiff, in manner, be rough, be rigid, be harsh, be brusque, hard, strong, tough, harsh, brusque, hard, rough, strident, dissonant, raucous | C12: =VLOOKUP(A12,[1]checker!$A:$C,1,FALSE) -> #N/A | D12: =VLOOKUP(A12,[1]checker!$A:$C,3,FALSE) -> #N/A | E12: =VLOOKUP(A12,'top 4000'!$B:$Q,3,FALSE) -> #N/A | F12: =VLOOKUP(A12,'top 4000'!$B:$Q,16,FALSE) -> #N/A
A13: กระดาษ | B13: paper | C13: =VLOOKUP(A13,[1]checker!$A:$C,1,FALSE) -> #N/A | D13: =VLOOKUP(A13,[1]checker!$A:$C,3,FALSE) -> #N/A | E13: =VLOOKUP(A13,'top 4000'!$B:$Q,3,FALSE) -> paper | F13: =VLOOKUP(A13,'top 4000'!$B:$Q,16,FALSE) -> 1020
A14: กระดูก | B14: bone, stingy, cheap | C14: =VLOOKUP(A14,[1]checker!$A:$C,1,FALSE) -> #N/A | D14: =VLOOKUP(A14,[1]checker!$A:$C,3,FALSE) -> #N/A | E14: =VLOOKUP(A14,'top 4000'!$B:$Q,3,FALSE) -> bone | F14: =VLOOKUP(A14,'top 4000'!$B:$Q,16,FALSE) -> 2193
... A244: เช้า | B244: morning (between 6am and 11am) | C244: =VLOOKUP(A244,[1]checker!$A:$C,1,FALSE) -> เช้า | D244: =VLOOKUP(A244,[1]checker!$A:$C,3,FALSE) -> morning | E244: =VLOOKUP(A244,'top 4000'!$B:$Q,3,FALSE) -> morning | F244: =VLOOKUP(A244,'top 4000'!$B:$Q,16,FALSE) -> 880
A245: เชิญ | C245: =VLOOKUP(A245,[1]checker!$A:$C,1,FALSE) -> เชิญ | D245: =VLOOKUP(A245,[1]checker!$A:$C,3,FALSE) -> invite | E245: =VLOOKUP(A245,'top 4000'!$B:$Q,3,FALSE) -> invite | F245: =VLOOKUP(A245,'top 4000'!$B:$Q,16,FALSE) -> 733
A246: เชื่อ | B246: believe, trust, to have faith in, rely on | C246: =VLOOKUP(A246,[1]checker!$A:$C,1,FALSE) -> เชื่อ | D246: =VLOOKUP(A246,[1]checker!$A:$C,3,FALSE) -> believe | E246: =VLOOKUP(A246,'top 4000'!$B:$Q,3,FALSE) -> believe | F246: =VLOOKUP(A246,'top 4000'!$B:$Q,16,FALSE) -> 223
A247: เชื้อ | B247: bacteria, microbe, yeast, germ | C247: =VLOOKUP(A247,[1]checker!$A:$C,1,FALSE) -> #N/A | D247: =VLOOKUP(A247,[1]checker!$A:$C,3,FALSE) -> #N/A | E247: =VLOOKUP(A247,'top 4000'!$B:$Q,3,FALSE) -> infection; bacteria; sperm | F247: =VLOOKUP(A247,'top 4000'!$B:$Q,16,FALSE) -> 1485
A248: ใช่ | B248: yes, I agree, correct, right, indeed, that's so | C248: =VLOOKUP(A248,[1]checker!$A:$C,1,FALSE) -> ใช่ | D248: =VLOOKUP(A248,[1]checker!$A:$C,3,FALSE) -> correct | E248: =VLOOKUP(A248,'top 4000'!$B:$Q,3,FALSE) -> correct | F248: =VLOOKUP(A248,'top 4000'!$B:$Q,16,FALSE) -> 184
A249: ใช้ | B249: use, emply, exploit, utilize, resort to, implement | C249: =VLOOKUP(A249,[1]checker!$A:$C,1,FALSE) -> ใช้ | D249: =VLOOKUP(A249,[1]checker!$A:$C,3,FALSE) -> use | E249: =VLOOKUP(A249,'top 4000'!$B:$Q,3,FALSE) -> use | F249: =VLOOKUP(A249,'top 4000'!$B:$Q,16,FALSE) -> 50
A250: ซ่อน | B250: conceal, hide | C250: =VLOOKUP(A250,[1]checker!$A:$C,1,FALSE) -> #N/A | D250: =VLOOKUP(A250,[1]checker!$A:$C,3,FALSE) -> #N/A | E250: =VLOOKUP(A250,'top 4000'!$B:$Q,3,FALSE) -> conceal; hide | F250: =VLOOKUP(A250,'top 4000'!$B:$Q,16,FALSE) -> 1512
A251: ซ้าย | B251: left (direction) | C251: =VLOOKUP(A251,[1]checker!$A:$C,1,FALSE) -> ซ้าย | D251: =VLOOKUP(A251,[1]checker!$A:$C,3,FALSE) -> left | E251: =VLOOKUP(A251,'top 4000'!$B:$Q,3,FALSE) -> left | F251: =VLOOKUP(A251,'top 4000'!$B:$Q,16,FALSE) -> 994
A252: ซ้ำ | B252: repeat, recure, reiterate | C252: =VLOOKUP(A252,[1]checker!$A:$C,1,FALSE) -> ซ้ำ | D252: =VLOOKUP(A252,[1]checker!$A:$C,3,FALSE) -> repeatedly | E252: =VLOOKUP(A252,'top 4000'!$B:$Q,3,FALSE) -> repeatedly | F252: =VLOOKUP(A252,'top 4000'!$B:$Q,16,FALSE) -> 471
A253: ซิ | B253: [particle which conveys urgency] | C253: =VLOOKUP(A253,[1]checker!$A:$C,1,FALSE) -> #N/A | D253: =VLOOKUP(A253,[1]checker!$A:$C,3,FALSE) -> #N/A | E253: =VLOOKUP(A253,'top 4000'!$B:$Q,3,FALSE) -> #N/A | F253: =VLOOKUP(A253,'top 4000'!$B:$Q,16,FALSE) -> #N/A
A254: ซีก | B254: section, piece, part, portion | C254: =VLOOKUP(A254,[1]checker!$A:$C,1,FALSE) -> #N/A | D254: =VLOOKUP(A254,[1]checker!$A:$C,3,FALSE) -> #N/A | E254: =VLOOKUP(A254,'top 4000'!$B:$Q,3,FALSE) -> piece; section; part | F254: =VLOOKUP(A254,'top 4000'!$B:$Q,16,FALSE) -> 3280
A255: ซึ่ง | B255: that, which, who, whose, whom | C255: =VLOOKUP(A255,[1]checker!$A:$C,1,FALSE) -> ซึ่ง | D255: =VLOOKUP(A255,[1]checker!$A:$C,3,FALSE) -> which | E255: =VLOOKUP(A255,'top 4000'!$B:$Q,3,FALSE) -> which | F255: =VLOOKUP(A255,'top 4000'!$B:$Q,16,FALSE) -> 46
A256: ซื่อ | B256: faithful, loyal, honest | C256: =VLOOKUP(A256,[1]checker!$A:$C,1,FALSE) -> #N/A | D256: =VLOOKUP(A256,[1]checker!$A:$C,3,FALSE) -> #N/A | E256: =VLOOKUP(A256,'top 4000'!$B:$Q,3,FALSE) -> faithfully; honest | F256: =VLOOKUP(A256,'top 4000'!$B:$Q,16,FALSE) -> 3039
A257: ซื้อ | B257: buy or purchase | C257: =VLOOKUP(A257,[1]checker!$A:$C,1,FALSE) -> ซื้อ | D257: =VLOOKUP(A257,[1]checker!$A:$C,3,FALSE) -> buy | E257: =VLOOKUP(A257,'top 4000'!$B:$Q,3,FALSE) -> buy | F257: =VLOOKUP(A257,'top 4000'!$B:$Q,16,FALSE) -> 245
... A576: พ้อง | B576: synonymous, alike-sounding, identical, in agreement, coincident, simultaneous, allied | C576: =VLOOKUP(A576,[1]checker!$A:$C,1,FALSE) -> #N/A | D576: =VLOOKUP(A576,[1]checker!$A:$C,3,FALSE) -> #N/A | E576: =VLOOKUP(A576,'top 4000'!$B:$Q,3,FALSE) -> coincide | F576: =VLOOKUP(A576,'top 4000'!$B:$Q,16,FALSE) -> 3603
A577: พะยาน [modern พยาน] | B577: witness | C577: =VLOOKUP(A577,[1]checker!$A:$C,1,FALSE) -> #N/A | D577: =VLOOKUP(A577,[1]checker!$A:$C,3,FALSE) -> #N/A | E577: =VLOOKUP(A577,'top 4000'!$B:$Q,3,FALSE) -> #N/A | F577: 1822
A578: พัก | B578: stay, rest, break | C578: =VLOOKUP(A578,[1]checker!$A:$C,1,FALSE) -> พัก | D578: =VLOOKUP(A578,[1]checker!$A:$C,3,FALSE) -> to rest | E578: =VLOOKUP(A578,'top 4000'!$B:$Q,3,FALSE) -> to rest | F578: =VLOOKUP(A578,'top 4000'!$B:$Q,16,FALSE) -> 529
A579: พัน | B579: thousand | C579: =VLOOKUP(A579,[1]checker!$A:$C,1,FALSE) -> พัน | D579: =VLOOKUP(A579,[1]checker!$A:$C,3,FALSE) -> thousand; to tie | E579: =VLOOKUP(A579,'top 4000'!$B:$Q,3,FALSE) -> thousand; to tie | F579: =VLOOKUP(A579,'top 4000'!$B:$Q,16,FALSE) -> 783
A580: พันธ์ | B580: unite, connect | C580: =VLOOKUP(A580,[1]checker!$A:$C,1,FALSE) -> #N/A | D580: =VLOOKUP(A580,[1]checker!$A:$C,3,FALSE) -> #N/A | E580: =VLOOKUP(A580,'top 4000'!$B:$Q,3,FALSE) -> #N/A | F580: =VLOOKUP(A580,'top 4000'!$B:$Q,16,FALSE) -> #N/A
A581: พา | B581: bring, lead, guide | C581: =VLOOKUP(A581,[1]checker!$A:$C,1,FALSE) -> พา | D581: =VLOOKUP(A581,[1]checker!$A:$C,3,FALSE) -> lead; carry | E581: =VLOOKUP(A581,'top 4000'!$B:$Q,3,FALSE) -> lead; carry | F581: =VLOOKUP(A581,'top 4000'!$B:$Q,16,FALSE) -> 363
A582: พาณิชย์ | B582: commercial, pertaining to commerce | C582: =VLOOKUP(A582,[1]checker!$A:$C,1,FALSE) -> #N/A | D582: =VLOOKUP(A582,[1]checker!$A:$C,3,FALSE) -> #N/A | E582: =VLOOKUP(A582,'top 4000'!$B:$Q,3,FALSE) -> commerce | F582: =VLOOKUP(A582,'top 4000'!$B:$Q,16,FALSE) -> 1663
A583: พาย | B583: row, paddle | C583: =VLOOKUP(A583,[1]checker!$A:$C,1,FALSE) -> #N/A | D583: =VLOOKUP(A583,[1]checker!$A:$C,3,FALSE) -> #N/A | E583: =VLOOKUP(A583,'top 4000'!$B:$Q,3,FALSE) -> row; paddle; scull | F583: =VLOOKUP(A583,'top 4000'!$B:$Q,16,FALSE) -> 3417
A584: พาล | B584: belligerent, bullying | C584: =VLOOKUP(A584,[1]checker!$A:$C,1,FALSE) -> #N/A | D584: =VLOOKUP(A584,[1]checker!$A:$C,3,FALSE) -> #N/A | E584: =VLOOKUP(A584,'top 4000'!$B:$Q,3,FALSE) -> #N/A | F584: =VLOOKUP(A584,'top 4000'!$B:$Q,16,FALSE) -> #N/A
A585: พาหนะ | B585: vehicle, carrier, transport | C585: =VLOOKUP(A585,[1]checker!$A:$C,1,FALSE) -> #N/A | D585: =VLOOKUP(A585,[1]checker!$A:$C,3,FALSE) -> #N/A | E585: =VLOOKUP(A585,'top 4000'!$B:$Q,3,FALSE) -> vehicle | F585: =VLOOKUP(A585,'top 4000'!$B:$Q,16,FALSE) -> 3318
A586: พิจารณา | B586: consider, inquire, meditate | C586: =VLOOKUP(A586,[1]checker!$A:$C,1,FALSE) -> พิจารณา | D586: =VLOOKUP(A586,[1]checker!$A:$C,3,FALSE) -> consider | E586: =VLOOKUP(A586,'top 4000'!$B:$Q,3,FALSE) -> consider | F586: =VLOOKUP(A586,'top 4000'!$B:$Q,16,FALSE) -> 357
A587: พิธี | B587: ceremony, event | C587: =VLOOKUP(A587,[1]checker!$A:$C,1,FALSE) -> พิธี | D587: =VLOOKUP(A587,[1]checker!$A:$C,3,FALSE) -> ceremony | E587: =VLOOKUP(A587,'top 4000'!$B:$Q,3,FALSE) -> ceremony | F587: =VLOOKUP(A587,'top 4000'!$B:$Q,16,FALSE) -> 588
A588: พิมพ์ | B588: print, type, imprint | C588: =VLOOKUP(A588,[1]checker!$A:$C,1,FALSE) -> พิมพ์ | D588: =VLOOKUP(A588,[1]checker!$A:$C,3,FALSE) -> print; type | E588: =VLOOKUP(A588,'top 4000'!$B:$Q,3,FALSE) -> print; type | F588: =VLOOKUP(A588,'top 4000'!$B:$Q,16,FALSE) -> 361
A589: พิเศษ | B589: special, extraordinary | C589: =VLOOKUP(A589,[1]checker!$A:$C,1,FALSE) -> พิเศษ | D589: =VLOOKUP(A589,[1]checker!$A:$C,3,FALSE) -> special | E589: =VLOOKUP(A589,'top 4000'!$B:$Q,3,FALSE) -> special | F589: =VLOOKUP(A589,'top 4000'!$B:$Q,16,FALSE) -> 358
... A752: ล้ม | B752: fall down | C752: =VLOOKUP(A752,[1]checker!$A:$C,1,FALSE) -> #N/A | D752: =VLOOKUP(A752,[1]checker!$A:$C,3,FALSE) -> #N/A | E752: =VLOOKUP(A752,'top 4000'!$B:$Q,3,FALSE) -> abolish; die; fall down | F752: =VLOOKUP(A752,'top 4000'!$B:$Q,16,FALSE) -> 1237
A753: ลวง | B753: deceive | C753: =VLOOKUP(A753,[1]checker!$A:$C,1,FALSE) -> #N/A | D753: =VLOOKUP(A753,[1]checker!$A:$C,3,FALSE) -> #N/A | E753: =VLOOKUP(A753,'top 4000'!$B:$Q,3,FALSE) -> deceive | F753: =VLOOKUP(A753,'top 4000'!$B:$Q,16,FALSE) -> 3790 | H753: หลอกลวง
A754: ล่วง | B754: exceed, overstep, pass, go beyond | C754: =VLOOKUP(A754,[1]checker!$A:$C,1,FALSE) -> #N/A | D754: =VLOOKUP(A754,[1]checker!$A:$C,3,FALSE) -> #N/A | E754: =VLOOKUP(A754,'top 4000'!$B:$Q,3,FALSE) -> #N/A | F754: =VLOOKUP(A754,'top 4000'!$B:$Q,16,FALSE) -> #N/A
A755: ล้วน | B755: pure, absolute, pristine | C755: =VLOOKUP(A755,[1]checker!$A:$C,1,FALSE) -> ล้วน | D755: =VLOOKUP(A755,[1]checker!$A:$C,3,FALSE) -> completely; pure, absolute | E755: =VLOOKUP(A755,'top 4000'!$B:$Q,3,FALSE) -> completely; pure, absolute | F755: =VLOOKUP(A755,'top 4000'!$B:$Q,16,FALSE) -> 574
A756: ลอง | B756: try, test, experiment with, try out | C756: =VLOOKUP(A756,[1]checker!$A:$C,1,FALSE) -> ลอง | D756: =VLOOKUP(A756,[1]checker!$A:$C,3,FALSE) -> to try | E756: =VLOOKUP(A756,'top 4000'!$B:$Q,3,FALSE) -> to try | F756: =VLOOKUP(A756,'top 4000'!$B:$Q,16,FALSE) -> 672
A757: ลอย | B757: float, set afloat or adrift, waft through the air | C757: =VLOOKUP(A757,[1]checker!$A:$C,1,FALSE) -> #N/A | D757: =VLOOKUP(A757,[1]checker!$A:$C,3,FALSE) -> #N/A | E757: =VLOOKUP(A757,'top 4000'!$B:$Q,3,FALSE) -> float | F757: =VLOOKUP(A757,'top 4000'!$B:$Q,16,FALSE) -> 1169
A758: ละ | B758: each, every, one at a time | C758: =VLOOKUP(A758,[1]checker!$A:$C,1,FALSE) -> ละ | D758: =VLOOKUP(A758,[1]checker!$A:$C,3,FALSE) -> each | E758: =VLOOKUP(A758,'top 4000'!$B:$Q,3,FALSE) -> each | F758: =VLOOKUP(A758,'top 4000'!$B:$Q,16,FALSE) -> 173
A759: ละคร | B759: theatrica presentation | C759: =VLOOKUP(A759,[1]checker!$A:$C,1,FALSE) -> ละคร | D759: =VLOOKUP(A759,[1]checker!$A:$C,3,FALSE) -> drama | E759: =VLOOKUP(A759,'top 4000'!$B:$Q,3,FALSE) -> drama | F759: =VLOOKUP(A759,'top 4000'!$B:$Q,16,FALSE) -> 658
A760: ละลาย | B760: dissolve, melt | C760: =VLOOKUP(A760,[1]checker!$A:$C,1,FALSE) -> #N/A | D760: =VLOOKUP(A760,[1]checker!$A:$C,3,FALSE) -> #N/A | E760: =VLOOKUP(A760,'top 4000'!$B:$Q,3,FALSE) -> melt | F760: =VLOOKUP(A760,'top 4000'!$B:$Q,16,FALSE) -> 2808
A761: ละออง | B761: dust, spray, mist, particles, fine particles, powder, fall-out | C761: =VLOOKUP(A761,[1]checker!$A:$C,1,FALSE) -> #N/A | D761: =VLOOKUP(A761,[1]checker!$A:$C,3,FALSE) -> #N/A | E761: =VLOOKUP(A761,'top 4000'!$B:$Q,3,FALSE) -> #N/A | F761: =VLOOKUP(A761,'top 4000'!$B:$Q,16,FALSE) -> #N/A
A762: ละเอียด | B762: detailed, exact, delicate, fine, powdered, finely powdered, meticulous, careful, thorough, methodical | C762: =VLOOKUP(A762,[1]checker!$A:$C,1,FALSE) -> ละเอียด | D762: =VLOOKUP(A762,[1]checker!$A:$C,3,FALSE) -> detailed | E762: =VLOOKUP(A762,'top 4000'!$B:$Q,3,FALSE) -> detailed | F762: =VLOOKUP(A762,'top 4000'!$B:$Q,16,FALSE) -> 791
A763: ลัก | B763: steal, pilfer, pinch, carry off | C763: =VLOOKUP(A763,[1]checker!$A:$C,1,FALSE) -> #N/A | D763: =VLOOKUP(A763,[1]checker!$A:$C,3,FALSE) -> #N/A | E763: =VLOOKUP(A763,'top 4000'!$B:$Q,3,FALSE) -> steal | F763: =VLOOKUP(A763,'top 4000'!$B:$Q,16,FALSE) -> 2079
A764: ลักษณะ | B764: characteristic, form, attribute, quality, pattern, style | C764: =VLOOKUP(A764,[1]checker!$A:$C,1,FALSE) -> ลักษณะ | D764: =VLOOKUP(A764,[1]checker!$A:$C,3,FALSE) -> characteristic; attribute | E764: =VLOOKUP(A764,'top 4000'!$B:$Q,3,FALSE) -> characteristic; attribute | F764: =VLOOKUP(A764,'top 4000'!$B:$Q,16,FALSE) -> 365
A765: ลัง | B765: box, case, casket, crate, box, case, packing,case, chest, species,of,marine,fish, Rastrelliger,brachysomus | C765: =VLOOKUP(A765,[1]checker!$A:$C,1,FALSE) -> #N/A | D765: =VLOOKUP(A765,[1]checker!$A:$C,3,FALSE) -> #N/A | E765: =VLOOKUP(A765,'top 4000'!$B:$Q,3,FALSE) -> #N/A | F765: =VLOOKUP(A765,'top 4000'!$B:$Q,16,FALSE) -> #N/A
... A1000: โอรส | B1000: son | C1000: =VLOOKUP(A1000,[1]checker!$A:$C,1,FALSE) -> #N/A | D1000: =VLOOKUP(A1000,[1]checker!$A:$C,3,FALSE) -> #N/A | E1000: =VLOOKUP(A1000,'top 4000'!$B:$Q,3,FALSE) -> #N/A | F1000: =VLOOKUP(A1000,'top 4000'!$B:$Q,16,FALSE) -> #N/A
A1003: This list has been downloaded from: Thai Frequency Lists with English Definitions [http://womenlearnthai.com/index.php/thai-frequency-lists-with-english-definitions/ ]
A1004: TIP: Watch that post for new or updated lists

Sheet other
A2: other: | B2: https://www.thethailandlife.com/100-thai-words-improve-grammar
A3: 1. come – มา (maa)
A4: 2. get – ได้รับ (dai-rub)
A5: 3. give – ให้ (hai)
A6: 4. go – ไป (bpai)
A7: 5. keep – เก็บ (geb)
A8: 6. let – ปล่อยให้ (ploi- hai)
A9: 7. make – ทำให้ (thum-hai)
A10: 8. put – วาง (waang)
A11: 9. seem (seems like/looks like) – ดูเหมือน (duu-muang)
A12: 10. take time – ใช้เวลา (chai-ve-la)
A13: Correction here: The video is incorrect. This actually means to “take time”, or to “spend time”. The general word for ‘take' is เอา (ao). To say “take it” to someone, you can use “ao bpai” – เอาไป.
A14: 11. be – เป็น (bpen)
... A104: 100. yes – ใช่ (chai)
